langid/__init__.py
langid/langid.py
langid/tools/__init__.py
langid/tools/featWeights.py
langid/tools/printfeats.py
langid/train/BLweight.py
langid/train/DFfeatureselect.py
langid/train/IGweight.py
langid/train/LDfeatureselect.py
langid/train/NBtrain.py
langid/train/__init__.py
langid/train/common.py
langid/train/index.py
langid/train/scanner.py
langid/train/tokenize.py
langid/train/train.py
langid2-1.1.7.dist-info/licenses/LICENSE
langid2-1.1.7.dist-info/METADATA
langid2-1.1.7.dist-info/WHEEL
langid2-1.1.7.dist-info/top_level.txt
langid2-1.1.7.dist-info/RECORD
