Metadata-Version: 2.4
Name: langid2
Version: 1.1.7
Home-page: https://github.com/saffsd/langid.py
Author: Marco Lui
Author-email: saffsd@gmail.com
License-File: LICENSE
Requires-Dist: numpy
Dynamic: author
Dynamic: author-email
Dynamic: home-page
Dynamic: license-file
